{
    "search_title": "How affordable is rent in your area?",
    "search_placeholder": "Enter the name of your local authority area to find out",
    "search_error": "Sorry, we don't recognise this query. Please enter the name of your local area",
    "search_submit_text": "Search",
    "search_screenreader_title_helper": "Results for ",
    "search_screenreader_autosuggest_help": " results are available, use up and down arrow keys to navigate.",
    "meta:url": "",
    "meta:title": "",
    "meta:description": "",
    "meta:type": "article",
    "meta:site_name": "BBC News",
    "meta:locale": "en_GB",
    "meta:publisher": "https://www.facebook.com/bbcnews/",
    "meta:section": "",
    "meta:image": "",
    "meta:twitter:card": "summary_large_image",
    "meta:twitter:site": "@BBCNews",
    "meta:twitter:creator": "@BBCNews",
    "meta:twitter:title": "",
    "meta:twitter:description": "",
    "meta:twitter:image": "",
    "browser_support_message": "This interactive feature is optimised for modern web browsers.",
    "legacy_ie_message": "This site is optimised for modern web browsers, and does not fully support your version of Internet Explorer"
}
